setup.py
thingstore/__init__.py
thingstore.egg-info/PKG-INFO
thingstore.egg-info/SOURCES.txt
thingstore.egg-info/dependency_links.txt
thingstore.egg-info/requires.txt
thingstore.egg-info/top_level.txt