Metadata-Version: 1.0
Name: thingstore
Version: 0.0.1b
Summary: store things
Home-page: https://github.com/uniphil/thingstore
Author: Philip Schleihauf
Author-email: uniphil@gmail.com
License: GNU Public License v3
Platform: UNKNOWN
